easetx/__init__.py
easetx/feature_extractor.py
easetx/predictor_extractor.py
easetx/scorer.py
easetx/text_comparison.py
easetx/text_set.py
easetx/util_functions.py
easetx-0.1.5.data/scripts/download_nltk_data.py
easetx-0.1.5.dist-info/licenses/LICENSE
easetx-0.1.5.dist-info/METADATA
easetx-0.1.5.dist-info/WHEEL
easetx-0.1.5.dist-info/top_level.txt
easetx-0.1.5.dist-info/RECORD
