Metadata-Version: 2.4
Name: easetx
Version: 0.1.5
Summary: EASE-TX: Enhanced AI Scoring Engine for Text Analysis
Home-page: https://github.com/mogaio/EASE-TX
Author: Islam A. Hassan
Author-email: "Islam A. Hassan" <mohamedi@tcd.ie>
License: Apache 2.0
Project-URL: Homepage, https://github.com/mogaio/EASE-TX
Project-URL: Issues, https://github.com/mogaio/EASE-TX/issues
Classifier: Development Status :: 3 - Alpha
Classifier: Intended Audience :: Education
Classifier: Intended Audience :: Science/Research
Classifier: License :: OSI Approved :: Apache Software License
Classifier: Programming Language :: Python :: 3
Classifier: Programming Language :: Python :: 3.7
Classifier: Programming Language :: Python :: 3.8
Classifier: Programming Language :: Python :: 3.9
Classifier: Topic :: Education
Classifier: Topic :: Scientific/Engineering :: Artificial Intelligence
Classifier: Topic :: Text Processing :: Linguistic
Requires-Python: >=3.7
License-File: LICENSE
Requires-Dist: numpy>=1.16.5
Requires-Dist: scipy>=1.7.0
Requires-Dist: scikit-learn>=0.24.0
Requires-Dist: nltk>=3.6.0
Requires-Dist: python-Levenshtein>=0.12.0
Dynamic: author
Dynamic: home-page
Dynamic: license-file
Dynamic: requires-python
